structure_detective/__init__.py
structure_detective/constants.py
structure_detective/de/structure.py
structure_detective/de/trans_structure.py
structure_detective/en/structure.py
structure_detective/en/trans_structure.py
structure_detective/es/morph_translation.py
structure_detective/es/structure.py
structure_detective/es/trans_structure.py
structure_detective/lib.py
structure_detective/structure.py
structure_detective-0.1.9.dist-info/METADATA
structure_detective-0.1.9.dist-info/WHEEL
structure_detective-0.1.9.dist-info/RECORD
