Metadata-Version: 2.1
Name: structure-detective
Version: 0.1.9
Summary: Spacy component for parsing sentence
Author: Phoenix.Grey
Author-email: phoenix.grey0108@gmail.com
Requires-Python: >=3.12,<4.0
Classifier: Programming Language :: Python :: 3
Classifier: Programming Language :: Python :: 3.12
Classifier: Programming Language :: Python :: 3.13
Requires-Dist: spacy (==3.7.5)
